grateful_logging/__init__.py
grateful_logging/__main__.py
grateful_logging/cli.py
grateful_logging/configure.py
grateful_logging/assets/__init__.py
grateful_logging/assets/config-example.json
grateful_logging/formatter/__init__.py
grateful_logging/formatter/json.py
grateful_logging/handler/__init__.py
grateful_logging/handler/event_loop_queue.py
grateful_logging/handler/queue.py
grateful_logging/parser/__init__.py
grateful_logging/parser/base.py
grateful_logging/parser/json_file.py
grateful_logging-0.0.21.data/data/grateful_logging/assets/config-example.json
grateful_logging-0.0.21.dist-info/LICENSE
grateful_logging-0.0.21.dist-info/METADATA
grateful_logging-0.0.21.dist-info/WHEEL
grateful_logging-0.0.21.dist-info/top_level.txt
grateful_logging-0.0.21.dist-info/RECORD
