Metadata-Version: 2.1
Name: grateful_logging
Version: 0.0.21
Summary: modern and easy-to-use logging configuration library inspired by the tutorial by mCoding
Author: axdjuraev
Author-email: <axdjuraev@gmail.com>
License-File: LICENSE
